market_research/__init__.py
market_research/analysis/__init__.py
market_research/analysis/sentimentmanager.py
market_research/analysis/textmanager.py
market_research/scraper/__init__.py
market_research/scraper/_scaper_scheme.py
market_research/scraper/models/__init__.py
market_research/scraper/models/model_p.py
market_research/scraper/models/model_s.py
market_research/scraper/models/model_sjp.py
market_research/scraper/rtings/__init__.py
market_research/scraper/rtings/rtings.py
market_research/scraper/rtings/rurlsearcher.py
market_research/scraper/rtings/rvisualizer.py
market_research/tools/__init__.py
market_research/tools/aimanager.py
market_research/tools/filemanager.py
market_research/tools/installer.py
market_research/tools/webdriver.py
getmodelspec-1.362.dist-info/METADATA
getmodelspec-1.362.dist-info/WHEEL
getmodelspec-1.362.dist-info/entry_points.txt
getmodelspec-1.362.dist-info/top_level.txt
getmodelspec-1.362.dist-info/RECORD
